money.v
//`timescale 1ns / 1ps
module money(CLK, M0, M1, M2, M3, M4, M5, ti , wi, ci, B1, B2, B3, C1, C2, C3, C4, rr, out, To, Wo, Co, Bo, C,so, RRo);


//module port declaration
input CLK;
input M0;
input M1;
input M2;
input M3;
input M4;
input M5;
input ti;
input wi;
input ci;
input B1;
input B2;
input B3;
input C1;
input C2;
input C3;
input C4;
input rr;
output reg [7:0] out;
output reg To;
output reg Wo;
output reg Co;
output reg [2:0]Bo;
output reg [3:0]C;
output reg [9:0]so;
output reg [2:0]RRo;


//module parameter declaration
parameter ONE_DOLLAR = 1, TWO_DOLLAR = 2, FIVE_DOLLAR = 5, TEN_DOLLAR = 10, TWENTY_DOLLAR = 20;
parameter TEA = 5, COOKIES = 20, COFFEE = 7;
parameter CANDIES_TYPE1 = 10, CANDIES_TYPE2 = 20, CANDIES_TYPE3 = 25;
parameter CHOCOLATES_TYPE1 = 30, CHOCOLATES_TYPE2 = 10, CHOCOLATES_TYPE3 = 25, CHOCOLATES_TYPE4= 50;
parameter MAX_TRANSACTION = 3;

reg NumTea, NumCookies, NumCoffee;
reg NumCandiesType1, NumCandiesType2, NumCandiesType3;
reg NumChocolatesType1, NumChocolatesType2, NumChocolatesType3, NumChocolatesType4;
reg NumTransaction;
reg NumTenDollar, NumOneDollar, NumTwoDollar, NumFiveDollar;



//initial registers
initial begin
	out = 0;
	To = 0;
	NumTea = 3;
	NumCookies = 3;
	NumCoffee = 3;
	NumCandiesType1 = 3;
	NumCandiesType2 = 3;
	NumCandiesType3 = 3;
	NumChocolatesType1 = 3;
	NumChocolatesType2 = 3;
	NumChocolatesType3 = 3;
	NumChocolatesType4 = 3;
	so[0] = 0;
	NumTransaction = MAX_TRANSACTION;
	RRo = 0;
end

always @(posedge CLK)
begin
	if(rr)
	begin
		if(out >= TWENTY_DOLLAR) 
		begin
			out <= out - TWENTY_DOLLAR;
			RRo <= 2;
		end
		else if((out>= TEN_DOLLAR) && (out < TWENTY_DOLLAR)) 
		begin
			out <= out - TEN_DOLLAR;
			RRo <= 1;
		end
		else if((out >= FIVE_DOLLAR) && (out < TEN_DOLLAR)) 
		begin
			out <= out - FIVE_DOLLAR;
			RRo <= 4;
		end
		else if((out >= TWO_DOLLAR) && (out < FIVE_DOLLAR)) 
		begin
			out <= out - TWO_DOLLAR;
			RRo <= 3;
		end
		else if((out >= ONE_DOLLAR) && (out < TWO_DOLLAR)) 
		begin
			out <= out - ONE_DOLLAR;
			RRo <= 5;
		end
		else if(out == 0) 
		begin
			RRo = 0;
//			rr = 0;
		end
	end
	else
	begin
		if ((~M4) && (~M5))
		begin
			if (M0)            out <= out + TEN_DOLLAR;
			else if (M1)       out <= out + ONE_DOLLAR;
			else if (M2)       out <= out + TWO_DOLLAR;
			else if (M3)       out <= out + FIVE_DOLLAR;
			else if (ti && (out >= TEA) && NumTransaction)                  
				begin 
				if (NumTea)
				begin
				out <= out - TEA;
				To <= 1; 
				NumTea <= NumTea - 1;
				NumTransaction <= NumTransaction - 1;
				end 
				else
				so[0] <= 1;
				end
			else if (wi && (out >= COOKIES) && NumTransaction)              
				begin
				if (NumCookies)
				begin
				out <= out - COOKIES;
				Wo <= 1;
				NumCookies <= NumCookies - 1;
				NumTransaction <= NumTransaction - 1;
				end
				else
				so[1] <= 1;
				end
			else if (ci && (out >= COFFEE) && NumTransaction)               
				begin
				if (NumCoffee)
				begin
				out <= out - COFFEE;
				Co <= 1;
				NumCoffee <= NumCoffee - 1;
				NumTransaction <= NumTransaction - 1;
				end
				else
				so[2] <= 1;
				end
			else if (B1 && (out >= CANDIES_TYPE1) && NumTransaction)        
				begin
				if (NumCandiesType1)
				begin
				out <= out - CANDIES_TYPE1;
				Bo[0] <= 1;
				NumCandiesType1 <= NumCandiesType1 - 1;
				NumTransaction <= NumTransaction - 1;
				end
				else
				so[3] <= 1;
				end
			else if (B2 && (out >= CANDIES_TYPE2) && NumTransaction)        
				begin
				if (NumCandiesType2)
				begin
				out <= out - CANDIES_TYPE2;
				Bo[1] <= 1;
				NumCandiesType2 = NumCandiesType2 - 1;
				NumTransaction <= NumTransaction - 1;
				end
				else
				so[4] <= 1;
				end
			else if (B3 && (out >= CANDIES_TYPE3) && NumTransaction)        
				begin
				if (NumCandiesType3)
				begin
				out <= out - CANDIES_TYPE3;
				Bo[2] <= 1;
				NumCandiesType3 <= NumCandiesType3 - 1;
				NumTransaction <= NumTransaction - 1;
				end
				else
				so[5] <= 1;
				end
			else if (C1 && (out >= CHOCOLATES_TYPE1) && NumTransaction)     
				begin
				if (NumChocolatesType1)
				begin
				out <= out - CHOCOLATES_TYPE1;
				C[0] <= 1;
				NumChocolatesType1 = NumChocolatesType1 - 1;
				NumTransaction <= NumTransaction - 1;
				end
				else
					so[6] <= 1;
				end
			else if (C2 && (out >= CHOCOLATES_TYPE2) && NumTransaction)     
				begin
				if (NumChocolatesType2)
				begin
				out <= out - CHOCOLATES_TYPE2;
				C[1] <= 1;
				NumChocolatesType2 <= NumChocolatesType2 - 1;
				NumTransaction <= NumTransaction - 1;
				end
				else
				so[7] <= 1;
				end
			else if (C3 && (out >= CHOCOLATES_TYPE3) && NumTransaction)     
				begin
				if (NumChocolatesType3)
				begin
				out <= out - CHOCOLATES_TYPE3;
				C[2] <= 1;
				NumChocolatesType3 <= NumChocolatesType3 - 1;
				NumTransaction <= NumTransaction - 1;
				end
				else
				so[8] <= 1;
				end
			else if (C4 && (out >= CHOCOLATES_TYPE4) && NumTransaction)     
				begin
				if (NumChocolatesType4)
				begin
				out <= out - CHOCOLATES_TYPE4;
				C[3] <= 1;
				NumChocolatesType4 = NumChocolatesType4 - 1;
				NumTransaction <= NumTransaction - 1;
				end
				else
				so[9] <= 1;
				end
		end
		else
		begin
			if (ti && NumTransaction)                  
				begin 
				if (NumTea)
				begin
				To <= 1; 
				NumTea <= NumTea - 1;
				NumTransaction <= NumTransaction - 1;
				end 
				else
				so[0] <= 1;
				end
			else if (wi && NumTransaction)              
				begin
				if (NumCookies)
				begin
				Wo <= 1;
				NumCookies <= NumCookies - 1;
				NumTransaction <= NumTransaction - 1;
				end
				else
				so[1] <= 1;
				end
			else if (ci && NumTransaction)               
				begin
				if (NumCoffee)
				begin
				Co <= 1;
				NumCoffee <= NumCoffee - 1;
				NumTransaction <= NumTransaction - 1;
				end
				else
				so[2] <= 1;
				end
			else if (B1 && NumTransaction)        
				begin
				if (NumCandiesType1)
				begin
				Bo[0] <= 1;
				NumCandiesType1 <= NumCandiesType1 - 1;
				NumTransaction <= NumTransaction - 1;
				end
				else
				so[3] <= 1;
				end
			else if (B2 && NumTransaction)        
				begin
				if (NumCandiesType2)
				begin
				Bo[1] <= 1;
				NumCandiesType2 = NumCandiesType2 - 1;
				NumTransaction <= NumTransaction - 1;
				end
				else
				so[4] <= 1;
				end
			else if (B3 && NumTransaction)        
				begin
				if (NumCandiesType3)
				begin
				Bo[2] <= 1;
				NumCandiesType3 <= NumCandiesType3 - 1;
				NumTransaction <= NumTransaction - 1;
				end
				else
				so[5] <= 1;
				end
			else if (C1 && NumTransaction)     
				begin
				if (NumChocolatesType1)
				begin
				C[0] <= 1;
				NumChocolatesType1 = NumChocolatesType1 - 1;
				NumTransaction <= NumTransaction - 1;
				end
				else
				so[6] <= 1;
				end
			else if (C2 && NumTransaction)     
				begin
				if (NumChocolatesType2)
				begin
				C[1] <= 1;
				NumChocolatesType2 <= NumChocolatesType2 - 1;
				NumTransaction <= NumTransaction - 1;
				end
				else
				so[7] <= 1;
				end
			else if (C3 && NumTransaction)     
				begin
				if (NumChocolatesType3)
				begin
				C[2] <= 1;
				NumChocolatesType3 <= NumChocolatesType3 - 1;
				NumTransaction <= NumTransaction - 1;
				end
				else
				so[8] <= 1;
				end
			else if (C4 && NumTransaction)     
				begin
				if (NumChocolatesType4)
				begin
				C[3] <= 1;
				NumChocolatesType4 = NumChocolatesType4 - 1;
				NumTransaction <= NumTransaction - 1;
				end
				else
				so[9] <= 1;
				end
		end
	end
end

endmodule

tb_money.v
module tb_money;

reg CLK, M0, M1, M2, M3, M4, M5, ti , wi, ci, B1, B2, B3, C1, C2, C3, C4, rr;
wire [7:0] out;
wire To, Wo, Co;
wire [2:0]Bo;
wire [3:0]C;
wire [9:0]so;
wire [2:0]RRo;

initial begin
    CLK = 1'b0;
    M0 = 1'b0;
    M1 = 1'b0;
    M2 = 1'b0;
    M3 = 1'b0;
    M4 = 1'b0;
    M5 = 1'b0;
    ti = 1'b0;
    wi = 1'b0;
    ci = 1'b0;
    B1 = 1'b0;
    B2 = 1'b0;
    B3 = 1'b0;
    C1 = 1'b0;
    C2 = 1'b0;
    C3 = 1'b0;
    C4 = 1'b0;  
    rr = 1'b0;  
    forever #5 CLK = ~CLK;
end

initial begin
    $monitor("time=%d, clk = %b, M0=%b, M1=%b, M2=%b, M3=%b, ti=%b, wi=%b, ci=%b, B1=%b, B2=%b, B3=%b, C1=%b, C2=%b, C3=%b, C4=%b, out = %d, To = %b, rr = %b, RRo = %d",  $time, CLK, M0, M1, M2, M3, ti , wi, ci, B1, B2, B3, C1, C2, C3, C4, out, To, rr, RRo);
    $dumpfile("mywave.vcd");
    $dumpvars(0);
    #10 M0 = 1;
    #10 M0 = 0;
    #10 M1 = 1;
    #10 M1 = 0;
    #10 M2 = 1;
    #10 M2 = 0;
    #10 M3 = 1;
    #10 M3 = 0;
    #10 ti = 1;
    #10 ti = 0;
    #10 rr = 1;
    #100 rr = 0;
    #10 $finish;
end


money Money1 (
    .CLK(CLK),
    .M0(M0),
    .M1(M1),
    .M2(M2),
    .M3(M3),
    .M4(M4),
    .M5(M5),
    .ti(ti),
    .wi(wi),
    .ci(ci),
    .B1(B1),
    .B2(B2),
    .B3(B3),
    .C1(C1),
    .C2(C2),
    .C3(C3),
    .C4(C4),
    .out(out),
    .To(To),
    .Wo(Wo),
    .Co(Co),
    .Bo(Bo),
    .C(C),
    .so(so),
    .rr(rr),
    .RRo(RRo)
);

endmodule

mywave.vcd
$date
	Thu Mar 24 18:20:12 2022
$end
$version
	Icarus Verilog
$end
$timescale
	1s
$end
$scope module tb_money $end
$var wire 10 ! so [9:0] $end
$var wire 8 " out [7:0] $end
$var wire 1 # Wo $end
$var wire 1 $ To $end
$var wire 3 % RRo [2:0] $end
$var wire 1 & Co $end
$var wire 4 ' C [3:0] $end
$var wire 3 ( Bo [2:0] $end
$var reg 1 ) B1 $end
$var reg 1 * B2 $end
$var reg 1 + B3 $end
$var reg 1 , C1 $end
$var reg 1 - C2 $end
$var reg 1 . C3 $end
$var reg 1 / C4 $end
$var reg 1 0 CLK $end
$var reg 1 1 M0 $end
$var reg 1 2 M1 $end
$var reg 1 3 M2 $end
$var reg 1 4 M3 $end
$var reg 1 5 M4 $end
$var reg 1 6 M5 $end
$var reg 1 7 ci $end
$var reg 1 8 rr $end
$var reg 1 9 ti $end
$var reg 1 : wi $end
$scope module Money1 $end
$var wire 1 ) B1 $end
$var wire 1 * B2 $end
$var wire 1 + B3 $end
$var wire 1 , C1 $end
$var wire 1 - C2 $end
$var wire 1 . C3 $end
$var wire 1 / C4 $end
$var wire 1 0 CLK $end
$var wire 1 1 M0 $end
$var wire 1 2 M1 $end
$var wire 1 3 M2 $end
$var wire 1 4 M3 $end
$var wire 1 5 M4 $end
$var wire 1 6 M5 $end
$var wire 1 7 ci $end
$var wire 1 8 rr $end
$var wire 1 9 ti $end
$var wire 1 : wi $end
$var reg 3 ; Bo [2:0] $end
$var reg 4 < C [3:0] $end
$var reg 1 & Co $end
$var reg 1 = NumCandiesType1 $end
$var reg 1 > NumCandiesType2 $end
$var reg 1 ? NumCandiesType3 $end
$var reg 1 @ NumChocolatesType1 $end
$var reg 1 A NumChocolatesType2 $end
$var reg 1 B NumChocolatesType3 $end
$var reg 1 C NumChocolatesType4 $end
$var reg 1 D NumCoffee $end
$var reg 1 E NumCookies $end
$var reg 1 F NumTea $end
$var reg 1 G NumTransaction $end
$var reg 3 H RRo [2:0] $end
$var reg 1 $ To $end
$var reg 1 # Wo $end
$var reg 8 I out [7:0] $end
$var reg 10 J so [9:0] $end
$upscope $end
$upscope $end
$enddefinitions $end
#0
$dumpvars
bx0 J
b0 I
b0 H
1G
1F
1E
1D
1C
1B
1A
1@
1?
1>
1=
bx <
bx ;
0:
09
08
07
06
05
04
03
02
01
00
0/
0.
0-
0,
0+
0*
0)
bx (
bx '
x&
b0 %
0$
x#
b0 "
bx0 !
$end
#5
10
#10
00
11
#15
b1010 "
b1010 I
10
#20
00
01
#25
10
#30
00
12
#35
b1011 "
b1011 I
10
#40
00
02
#45
10
#50
00
13
#55
b1101 "
b1101 I
10
#60
00
03
#65
10
#70
00
14
#75
b10010 "
b10010 I
10
#80
00
04
#85
10
#90
00
19
#95
0G
0F
1$
b1101 "
b1101 I
10
#100
00
09
#105
10
#110
00
18
#115
b1 %
b1 H
b11 "
b11 I
10
#120
00
#125
b11 %
b11 H
b1 "
b1 I
10
#130
00
#135
b101 %
b101 H
b0 "
b0 I
10
#140
00
#145
b0 %
b0 H
10
#150
00
#155
10
#160
00
#165
10
#170
00
#175
10
#180
00
#185
10
#190
00
#195
10
#200
00
#205
10
#210
00
08
